django_websocket_server/__init__.py
django_websocket_server/admin.py
django_websocket_server/apps.py
django_websocket_server/messagetemplates.py
django_websocket_server/models.py
django_websocket_server/tests.py
django_websocket_server/urls.py
django_websocket_server/views.py
django_websocket_server/websocket_server.py
django_websocket_server/migrations/0001_initial.py
django_websocket_server/migrations/__init__.py
django_websocket_server/static/django_websocket_server/django_websocket_server.js
django_websocket_server/static/django_websocket_server/sodium.js
Django_Websocket_Server-0.1.1560515466.dist-info/METADATA
Django_Websocket_Server-0.1.1560515466.dist-info/WHEEL
Django_Websocket_Server-0.1.1560515466.dist-info/top_level.txt
Django_Websocket_Server-0.1.1560515466.dist-info/RECORD
